allure_unittest/__init__.py
allure_unittest/listener.py
allure_unittest/result.py
allure_unittest/run.py
allure_unittest/utils.py
allure_unittest-0.0.2.dist-info/LICENSE
allure_unittest-0.0.2.dist-info/METADATA
allure_unittest-0.0.2.dist-info/WHEEL
allure_unittest-0.0.2.dist-info/top_level.txt
allure_unittest-0.0.2.dist-info/RECORD
