Metadata-Version: 2.1
Name: allure-unittest
Version: 0.0.2
Summary: unittest Allure integration
Author-email: Sun Young <hu7433438@sohu.com>
Project-URL: Homepage, https://github.com/hu7433438/allure-unittest
Project-URL: Bug Tracker, https://github.com/hu7433438/allure-unittest/issues
Classifier: Development Status :: 2 - Pre-Alpha
Classifier: Programming Language :: Python :: 3
Classifier: Environment :: Plugins
Classifier: Operating System :: OS Independent
Classifier: License :: OSI Approved :: BSD License
Requires-Python: >=3.6
License-File: LICENSE
Requires-Dist: allure-python-commons
